README.rst
setup.py
src/fc_bench/__init__.py
src/fc_bench/bench.py
src/fc_bench/demos.py
src/fc_bench/demos_op.py
src/fc_bench.egg-info/PKG-INFO
src/fc_bench.egg-info/SOURCES.txt
src/fc_bench.egg-info/dependency_links.txt
src/fc_bench.egg-info/requires.txt
src/fc_bench.egg-info/top_level.txt