Metadata-Version: 1.1
Name: fc-bench
Version: 0.0.2
Summary: The fc_bench package ...
Home-page: http://www.math.univ-paris13.fr/~cuvelier/software/Python/fc-bench.html
Author: Francois Cuvelier
Author-email: cuvelier@math.univ-paris13.fr
License: BSD
Platform: Linux
Platform: Mac OS-X
Platform: Windows
Classifier: Topic :: Scientific/Engineering
